{"assets/Frame%20853.png":["assets/Frame%20853.png"],"assets/Frame%20854.png":["assets/Frame%20854.png"],"assets/Mask%20Group.png":["assets/Mask%20Group.png"],"assets/client_review.json":["assets/client_review.json"],"assets/contents.json":["assets/contents.json"],"assets/contents_updated.json":["assets/contents_updated.json"],"assets/footer-background.png":["assets/footer-background.png"],"assets/have_project_bg_image.png":["assets/have_project_bg_image.png"],"assets/home_page_image_one.png":["assets/home_page_image_one.png"],"assets/icons/company_creation.png":["assets/icons/company_creation.png"],"assets/icons/compliance.png":["assets/icons/compliance.png"],"assets/icons/corporate_filing.png":["assets/icons/corporate_filing.png"],"assets/icons/filing.png":["assets/icons/filing.png"],"assets/icons/lets_talk_bg.png":["assets/icons/lets_talk_bg.png"],"assets/icons/payroll.png":["assets/icons/payroll.png"],"assets/icons/reistration.png":["assets/icons/reistration.png"],"assets/million_logo.png":["assets/million_logo.png"],"assets/name_01.png":["assets/name_01.png"],"assets/our_office_image_one.png":["assets/our_office_image_one.png"],"assets/our_team_image_two.png":["assets/our_team_image_two.png"],"assets/page_contents.json":["assets/page_contents.json"],"assets/ref.txt":["assets/ref.txt"],"assets/ref2.txt":["assets/ref2.txt"],"assets/services.json":["assets/services.json"],"fonts/Poppins-Regular.ttf":["fonts/Poppins-Regular.ttf"],"packages/cupertino_icons/assets/CupertinoIcons.ttf":["packages/cupertino_icons/assets/CupertinoIcons.ttf"]}